.codecov.yml
.coveragerc
.flake8
.pre-commit-config.yaml
.readthedocs.yaml
CHANGELOG.rst
LICENSE
MANIFEST.in
README.rst
pyproject.toml
requirements-dev.txt
requirements-docs.txt
requirements-test.txt
requirements.txt
setup.py
./torchsample/__init__.py
./torchsample/__meta__.py
./torchsample/_nobatch.py
./torchsample/_sample.py
./torchsample/_version.py
./torchsample/coord.py
./torchsample/default.py
./torchsample/models.py
./torchsample/encoding/__init__.py
./torchsample/encoding/functional.py
./torchsample/encoding/oop.py
.github/workflows/docs.yaml
.github/workflows/pre-commit.yaml
.github/workflows/publish.yaml
.github/workflows/system_info.py
.github/workflows/test.yaml
assets/banner-white-bg-200w.png
assets/banner-white-bg-512w.png
assets/banner-white-bg.png
assets/logo-64w.png
assets/logo.png
docs/Installation.rst
docs/Makefile
docs/Overview.rst
docs/align_corners.rst
docs/conf.py
docs/generating_coordinates.rst
docs/genindex.rst
docs/index.rst
docs/make.bat
docs/models.rst
docs/nobatch.rst
docs/positional_encoding.rst
docs/py-modindex.rst
docs/requirements.txt
docs/sampling.rst
docs/source/changelog.rst
examples/nerf2d/README.rst
examples/nerf2d/main.py
examples/nerf2d/input/polite.jpg
examples/nerf2d/output/polite_pos-enc=False/1000.jpg
examples/nerf2d/output/polite_pos-enc=False/1200.jpg
examples/nerf2d/output/polite_pos-enc=False/1400.jpg
examples/nerf2d/output/polite_pos-enc=False/1600.jpg
examples/nerf2d/output/polite_pos-enc=False/1800.jpg
examples/nerf2d/output/polite_pos-enc=False/200.jpg
examples/nerf2d/output/polite_pos-enc=False/2000.jpg
examples/nerf2d/output/polite_pos-enc=False/400.jpg
examples/nerf2d/output/polite_pos-enc=False/600.jpg
examples/nerf2d/output/polite_pos-enc=False/800.jpg
examples/nerf2d/output/polite_pos-enc=True/1000.jpg
examples/nerf2d/output/polite_pos-enc=True/1200.jpg
examples/nerf2d/output/polite_pos-enc=True/1400.jpg
examples/nerf2d/output/polite_pos-enc=True/1600.jpg
examples/nerf2d/output/polite_pos-enc=True/1800.jpg
torchsample.egg-info/PKG-INFO
torchsample.egg-info/SOURCES.txt
torchsample.egg-info/dependency_links.txt
torchsample.egg-info/requires.txt
torchsample.egg-info/top_level.txt
