Metadata-Version: 2.1
Name: torchsample
Version: 0.1.0
Summary: Neural network sampling utilities.
Home-page: https://github.com/BrianPugh/torchsample
Author: Brian Pugh
Author-email: bnp117@gmail.com
License: apache-2.0
Platform: UNKNOWN
Classifier: Natural Language :: English
Classifier: Programming Language :: Python
Classifier: Programming Language :: Python :: 3
Classifier: Programming Language :: Python :: 3.8
Classifier: Programming Language :: Python :: 3.9
Classifier: Programming Language :: Python :: 3.10
Requires-Python: >=3.6
Provides-Extra: test
Provides-Extra: docs
Provides-Extra: dev
Provides-Extra: all
